topsis/__init__.py
topsis/__main__.py
Topsis_Pulkit_102003619-1.0.1.dist-info/LICENSE
Topsis_Pulkit_102003619-1.0.1.dist-info/METADATA
Topsis_Pulkit_102003619-1.0.1.dist-info/WHEEL
Topsis_Pulkit_102003619-1.0.1.dist-info/entry_points.txt
Topsis_Pulkit_102003619-1.0.1.dist-info/top_level.txt
Topsis_Pulkit_102003619-1.0.1.dist-info/RECORD
