Metadata-Version: 2.1
Name: Topsis-Pulkit-102003619
Version: 1.0.1
Summary: A Python package implementing TOPSIS technique.
Author: Pulkit
Author-email: pgirdhar_be20@thapar.edu
License: MIT
Classifier: License :: OSI Approved :: MIT License
Classifier: Programming Language :: Python :: 3.6
Classifier: Programming Language :: Python :: 3.7
Classifier: Programming Language :: Python :: 3.8
Classifier: Programming Language :: Python :: 3.9
Classifier: Programming Language :: Python :: 3.10
Classifier: Programming Language :: Python :: 3.11
License-File: LICENSE
Requires-Dist: pathlib
Requires-Dist: numpy
Requires-Dist: pandas
